{
    "Name" : "WX_US_Radar",
    "DataHandler" : "TMS",
    "Attributes" : {
        "TimeList" : "%baseurl%/WRAP/wrap-pri/data/WX_US_Radar/index.json",
        "File" : "%baseurl%/WRAP/wrap-pri/data/WX_US_Radar/%validtime%/%z%/%x%/%y%.png",
        "DataGrid" : {
            "MinZoom" : 0,
            "MaxZoom" : 5,
            "_BoundingBox" : {
                "West":-70.00000000000000,
                "South":16.00117465407314,
                "East":-62.00119161287849,
                "North":21.00000000000000
            }
        },
        "UpdateInterval" : 300
    }
}
